sambacc/__init__.py
sambacc/_version.py
sambacc/_xattr.py
sambacc/addc.py
sambacc/config.py
sambacc/container_dns.py
sambacc/ctdb.py
sambacc/inotify_waiter.py
sambacc/jfile.py
sambacc/join.py
sambacc/leader.py
sambacc/netcmd_loader.py
sambacc/nsswitch_loader.py
sambacc/opener.py
sambacc/passdb_loader.py
sambacc/passwd_loader.py
sambacc/paths.py
sambacc/permissions.py
sambacc/rados_opener.py
sambacc/samba_cmds.py
sambacc/simple_waiter.py
sambacc/smbconf_api.py
sambacc/smbconf_samba.py
sambacc/textfile.py
sambacc/typelets.py
sambacc/url_opener.py
sambacc/commands/__init__.py
sambacc/commands/addc.py
sambacc/commands/check.py
sambacc/commands/cli.py
sambacc/commands/common.py
sambacc/commands/config.py
sambacc/commands/ctdb.py
sambacc/commands/dcmain.py
sambacc/commands/dns.py
sambacc/commands/initialize.py
sambacc/commands/join.py
sambacc/commands/main.py
sambacc/commands/run.py
sambacc/commands/skips.py
sambacc/commands/users.py
sambacc/commands/remotecontrol/__init__.py
sambacc/commands/remotecontrol/main.py
sambacc/commands/remotecontrol/server.py
sambacc/commands/satellite/__init__.py
sambacc/commands/satellite/__main__.py
sambacc/commands/satellite/keybridge.py
sambacc/grpc/__init__.py
sambacc/grpc/backend.py
sambacc/grpc/server.py
sambacc/grpc/generated/__init__.py
sambacc/grpc/generated/control_pb2.py
sambacc/grpc/generated/control_pb2.pyi
sambacc/grpc/generated/control_pb2_grpc.py
sambacc/grpc/protobufs/__init__.py
sambacc/grpc/protobufs/control.proto
sambacc/kmip/__init__.py
sambacc/kmip/scope.py
sambacc/schema/__init__.py
sambacc/schema/conf-v0.schema.json
sambacc/schema/conf-v0.schema.yaml
sambacc/schema/conf_v0_schema.py
sambacc/schema/tool.py
sambacc/varlink/__init__.py
sambacc/varlink/endpoint.py
sambacc/varlink/keybridge.py
sambacc/varlink/server.py
sambacc/varlink/interfaces/__init__.py
sambacc/varlink/interfaces/org.samba.containers.keybridge.varlink
sambacc-0.7.data/data/share/sambacc/examples/addc.json
sambacc-0.7.dist-info/licenses/COPYING
sambacc-0.7.dist-info/METADATA
sambacc-0.7.dist-info/WHEEL
sambacc-0.7.dist-info/entry_points.txt
sambacc-0.7.dist-info/top_level.txt
sambacc-0.7.dist-info/RECORD
