Metadata-Version: 2.4
Name: sambacc
Version: 0.7
Summary: Samba Container Configurator
Home-page: https://github.com/samba-in-kubernetes/sambacc
Author: John Mulligan
Author-email: phlogistonjohn@asynchrono.us
License: GPL3
License-File: COPYING
Provides-Extra: validation
Requires-Dist: jsonschema>=4.10; extra == "validation"
Provides-Extra: yaml
Requires-Dist: PyYAML>=5.4; extra == "yaml"
Provides-Extra: toml
Requires-Dist: tomli; python_version < "3.11" and extra == "toml"
Provides-Extra: rados
Requires-Dist: rados; extra == "rados"
Provides-Extra: grpc
Requires-Dist: grpcio>=1.48; extra == "grpc"
Requires-Dist: protobuf>=3.19; extra == "grpc"
Provides-Extra: keybridge
Requires-Dist: varlink; extra == "keybridge"
Requires-Dist: PyKMIP; extra == "keybridge"
Dynamic: license-file
